{
  "lastUpdated": "2026-03-29T09:40:42Z",
  "results": {
    "mobile": {
      "home": {
        "performance": 61,
        "accessibility": 100,
        "bestPractices": 100,
        "seo": 100,
        "lcp": 6752.642534865061,
        "cls": 0.00075000000000000012,
        "tbt": 0
      },
      "about": {
        "performance": 60,
        "accessibility": 100,
        "bestPractices": 100,
        "seo": 100
      },
      "blog": {
        "performance": 59,
        "accessibility": 98,
        "bestPractices": 100,
        "seo": 100
      },
      "builds": {
        "performance": 75,
        "accessibility": 98,
        "bestPractices": 100,
        "seo": 100
      },
      "gems": {
        "performance": 67,
        "accessibility": 98,
        "bestPractices": 100,
        "seo": 100
      }
    },
    "desktop": {
      "home": {
        "performance": 96,
        "accessibility": 100,
        "bestPractices": 100,
        "seo": 100,
        "lcp": 1264.143832661523,
        "cls": 0.0006020000000000001,
        "tbt": 0
      },
      "about": {
        "performance": 93,
        "accessibility": 100,
        "bestPractices": 100,
        "seo": 100
      },
      "blog": {
        "performance": 94,
        "accessibility": 98,
        "bestPractices": 100,
        "seo": 100
      },
      "builds": {
        "performance": 95,
        "accessibility": 98,
        "bestPractices": 100,
        "seo": 100
      },
      "gems": {
        "performance": 94,
        "accessibility": 98,
        "bestPractices": 100,
        "seo": 100
      }
    }
  },
  "history": []
}
