{
  "lastUpdated": "2026-07-05T12:17:00.173Z",
  "results": {
    "mobile": {
      "home": {
        "performance": 73,
        "accessibility": 96,
        "bestPractices": 100,
        "seo": 100,
        "lcp": 4678.348074586844,
        "cls": 0.0010780000000000002,
        "tbt": 2.5,
        "agenticBrowsingPassed": 3,
        "agenticBrowsingTotal": 3
      },
      "about": {
        "performance": 63,
        "accessibility": 100,
        "bestPractices": 100,
        "seo": 100,
        "agenticBrowsingPassed": 3,
        "agenticBrowsingTotal": 3
      },
      "blog": {
        "performance": 63,
        "accessibility": 100,
        "bestPractices": 100,
        "seo": 100,
        "agenticBrowsingPassed": 3,
        "agenticBrowsingTotal": 3
      },
      "builds": {
        "performance": 64,
        "accessibility": 100,
        "bestPractices": 100,
        "seo": 100,
        "agenticBrowsingPassed": 3,
        "agenticBrowsingTotal": 3
      },
      "gems": {
        "performance": 64,
        "accessibility": 100,
        "bestPractices": 100,
        "seo": 100,
        "agenticBrowsingPassed": 3,
        "agenticBrowsingTotal": 3
      }
    },
    "desktop": {
      "home": {
        "performance": 99,
        "accessibility": 96,
        "bestPractices": 100,
        "seo": 100,
        "lcp": 866.703901919509,
        "cls": 0.0006730000000000001,
        "tbt": 0,
        "agenticBrowsingPassed": 3,
        "agenticBrowsingTotal": 3
      },
      "about": {
        "performance": 95,
        "accessibility": 100,
        "bestPractices": 100,
        "seo": 100,
        "agenticBrowsingPassed": 3,
        "agenticBrowsingTotal": 3
      },
      "blog": {
        "performance": 95,
        "accessibility": 100,
        "bestPractices": 100,
        "seo": 100,
        "agenticBrowsingPassed": 3,
        "agenticBrowsingTotal": 3
      },
      "builds": {
        "performance": 99,
        "accessibility": 100,
        "bestPractices": 100,
        "seo": 100,
        "agenticBrowsingPassed": 3,
        "agenticBrowsingTotal": 3
      },
      "gems": {
        "performance": 96,
        "accessibility": 100,
        "bestPractices": 100,
        "seo": 100,
        "agenticBrowsingPassed": 3,
        "agenticBrowsingTotal": 3
      }
    }
  },
  "history": []
}
